easai/__init__.py
easai/assistant/__init__.py
easai/assistant/assistant.py
easai/assistant/chat_console.py
easai/assistant/log.py
easai/assistant/tool.py
easai/assistant/tools/coding_tool.py
easai/utils/__init__.py
easai/utils/colored_logging_formatter.py
easai/utils/console_formatting.py
easai/utils/file_utils.py
easai/utils/json_key_value_fetcher.py
easai/utils/local_cache.py
easai/utils/sqlite_logging_handler.py
easai-0.0.11.dist-info/METADATA
easai-0.0.11.dist-info/WHEEL
easai-0.0.11.dist-info/licenses/LICENSE
easai-0.0.11.dist-info/RECORD
