Metadata-Version: 2.3
Name: easai
Version: 0.0.11
Summary: Tools to assist and automate.
Project-URL: Homepage, https://github.com/uncas/easai
Project-URL: Issues, https://github.com/uncas/easai/issues
Author-email: Ole Lynge Sørensen <olelynge@gmail.com>
License-File: LICENSE
Classifier: License :: OSI Approved :: MIT License
Classifier: Operating System :: OS Independent
Classifier: Programming Language :: Python :: 3
Requires-Python: >=3.8
